flask_neo4j.py
flask_neo4j.py.bak
Flask_Neo4j-0.5.1.dist-info/DESCRIPTION.rst
Flask_Neo4j-0.5.1.dist-info/METADATA
Flask_Neo4j-0.5.1.dist-info/RECORD
Flask_Neo4j-0.5.1.dist-info/WHEEL
Flask_Neo4j-0.5.1.dist-info/metadata.json
Flask_Neo4j-0.5.1.dist-info/top_level.txt
